ncnn-1.0.20250916.dist-info/RECORD
ncnn-1.0.20250916.dist-info/WHEEL
ncnn-1.0.20250916.dist-info/top_level.txt
ncnn-1.0.20250916.dist-info/METADATA
ncnn-1.0.20250916.dist-info/licenses/LICENSE.txt
ncnn/__init__.py
ncnn/ncnn.cpython-313-darwin.so
ncnn/utils/download.py
ncnn/utils/__init__.py
ncnn/utils/functional.py
ncnn/utils/visual.py
ncnn/utils/objects.py
ncnn/model_zoo/peleenetssd.py
ncnn/model_zoo/shufflenetv2.py
ncnn/model_zoo/yolov7.py
ncnn/model_zoo/yolov3.py
ncnn/model_zoo/retinaface.py
ncnn/model_zoo/yolov2.py
ncnn/model_zoo/squeezenetssd.py
ncnn/model_zoo/squeezenet.py
ncnn/model_zoo/model_zoo.py
ncnn/model_zoo/yolact.py
ncnn/model_zoo/rfcn.py
ncnn/model_zoo/__init__.py
ncnn/model_zoo/yolov8.py
ncnn/model_zoo/simplepose.py
ncnn/model_zoo/nanodet.py
ncnn/model_zoo/model_store.py
ncnn/model_zoo/mobilenetv2ssdlite.py
ncnn/model_zoo/mobilenetssd.py
ncnn/model_zoo/fasterrcnn.py
ncnn/model_zoo/mobilenetv3ssdlite.py
ncnn/model_zoo/yolov5.py
ncnn/model_zoo/yolov4.py
ncnn/.dylibs/libMoltenVK.dylib
